mkdocs_typer2/__init__.py
mkdocs_typer2/markdown.py
mkdocs_typer2/plugin.py
mkdocs_typer2/pretty.py
mkdocs_typer2/cli/__init__.py
mkdocs_typer2/cli/cli.py
mkdocs_typer2/cli/sub_cli.py
mkdocs_typer2-0.2.0.dist-info/METADATA
mkdocs_typer2-0.2.0.dist-info/WHEEL
mkdocs_typer2-0.2.0.dist-info/entry_points.txt
mkdocs_typer2-0.2.0.dist-info/licenses/LICENSE
mkdocs_typer2-0.2.0.dist-info/RECORD
