Metadata-Version: 2.4
Name: mkdocs-typer2
Version: 0.2.0
Summary: Mkdocs plugin for generating Typer CLI docs
License-File: LICENSE
Requires-Python: >=3.10
Requires-Dist: mkdocs>=1.6.1
Requires-Dist: pydantic>=2.9.2
Requires-Dist: typer>=0.12.5
